[
    {
        "avatarImage": "assets/images/mark-zuckerberg.jpg",
        "friendName": "Mark Zuckerberg one",
        "mutualFriends": "1 Bạn chung"
    },
    {
        "avatarImage": "assets/images/mark-zuckerberg.jpg",
        "friendName": "Mark Zuckerberg two",
        "mutualFriends": "2 Bạn chung"
    },
    {
        "avatarImage": "assets/images/mark-zuckerberg.jpg",
        "friendName": "Mark Zuckerberg three",
        "mutualFriends": "3 Bạn chung"
    },
    {
        "avatarImage": "assets/images/mark-zuckerberg.jpg",
        "friendName": "Mark Zuckerberg four",
        "mutualFriends": "4 Bạn chung"
    },
    {
        "avatarImage": "assets/images/mark-zuckerberg.jpg",
        "friendName": "Mark Zuckerberg five",
        "mutualFriends": "5 Bạn chung"
    },
    {
        "avatarImage": "assets/images/mark-zuckerberg.jpg",
        "friendName": "Mark Zuckerberg six",
        "mutualFriends": "6 Bạn chung"
    },
    {
        "avatarImage": "assets/images/mark-zuckerberg.jpg",
        "friendName": "Mark Zuckerberg seven",
        "mutualFriends": "7 Bạn chung"
    },
    {
        "avatarImage": "assets/images/mark-zuckerberg.jpg",
        "friendName": "Mark Zuckerberg eight",
        "mutualFriends": "8 Bạn chung"
    },
    {
        "avatarImage": "assets/images/mark-zuckerberg.jpg",
        "friendName": "Mark Zuckerberg nine",
        "mutualFriends": "9 Bạn chung"
    },
    {
        "avatarImage": "assets/images/mark-zuckerberg.jpg",
        "friendName": "Mark Zuckerberg ten",
        "mutualFriends": "10 Bạn chung"
    },
    {
        "avatarImage": "assets/images/mark-zuckerberg.jpg",
        "friendName": "Mark Zuckerberg one",
        "mutualFriends": "1 Bạn chung"
    },
    {
        "avatarImage": "assets/images/mark-zuckerberg.jpg",
        "friendName": "Mark Zuckerberg two",
        "mutualFriends": "2 Bạn chung"
    },
    {
        "avatarImage": "assets/images/mark-zuckerberg.jpg",
        "friendName": "Mark Zuckerberg three",
        "mutualFriends": "3 Bạn chung"
    },
    {
        "avatarImage": "assets/images/mark-zuckerberg.jpg",
        "friendName": "Mark Zuckerberg four",
        "mutualFriends": "4 Bạn chung"
    },
    {
        "avatarImage": "assets/images/mark-zuckerberg.jpg",
        "friendName": "Mark Zuckerberg five",
        "mutualFriends": "5 Bạn chung"
    },
    {
        "avatarImage": "assets/images/mark-zuckerberg.jpg",
        "friendName": "Mark Zuckerberg six",
        "mutualFriends": "6 Bạn chung"
    },
    {
        "avatarImage": "assets/images/mark-zuckerberg.jpg",
        "friendName": "Mark Zuckerberg seven",
        "mutualFriends": "7 Bạn chung"
    },
    {
        "avatarImage": "assets/images/mark-zuckerberg.jpg",
        "friendName": "Mark Zuckerberg eight",
        "mutualFriends": "8 Bạn chung"
    },
    {
        "avatarImage": "assets/images/mark-zuckerberg.jpg",
        "friendName": "Mark Zuckerberg nine",
        "mutualFriends": "9 Bạn chung"
    },
    {
        "avatarImage": "assets/images/mark-zuckerberg.jpg",
        "friendName": "Mark Zuckerberg ten",
        "mutualFriends": "10 Bạn chung"
    }
]